sanic_utils/__init__.py
sanic_utils/from_json.py
sanic_utils-0.1.1.dist-info/METADATA
sanic_utils-0.1.1.dist-info/WHEEL
sanic_utils-0.1.1.dist-info/top_level.txt
sanic_utils-0.1.1.dist-info/RECORD
