Metadata-Version: 2.1
Name: sanic-utils
Version: 0.1.1
Summary: A suite of sanic sanic_utils
Home-page: https://github.com/chivandikwa/sanic-utils
Author: Thulani Chivandikwa
Author-email: chivandikwa.t@gmail.com
License: UNKNOWN
Platform: UNKNOWN
Classifier: Programming Language :: Python :: 3
Classifier: License :: OSI Approved :: MIT License
Classifier: Operating System :: OS Independent
Requires-Python: >=3.7
Requires-Dist: sanic (==20.6.3)
Requires-Dist: dataclasses (==0.6)
Requires-Dist: dataclasses-json (==0.5.1)
